{
	"Version": 3,
	"FileReferences": {
		"Moc": "마리live2d.moc3",
		"Textures": [
			"마리live2d.2048/texture_00.png"
		],
		"Physics": "마리live2d.physics3.json",
		"DisplayInfo": "마리live2d.cdi3.json",
		"Motions": {
			"Tilt": [
				{
					"File": "anim/갸우뚱.motion3.json"
				}
			],
			"Random": [
				{
					"File": "anim/랜덤 재생.motion3.json"
				}
			],
			"Clicked": [
				{
					"File": "anim/클릭.motion3.json"
				}
			],
			"ClickAlt": [
				{
					"File": "anim/뾰잉.motion3.json"
				}
			],
			"IdleGround": [
				{
					"File": "anim/Blink.motion3.json"
				},
				{
					"File": "anim/WaitLong.motion3.json"
				},
				{
					"File": "anim/WaitMedium.motion3.json"
				},
				{
					"File": "anim/WaitShort.motion3.json"
				}
			],
			"IdleSky": [
				{
					"File": "anim/SkyStare.motion3.json"
				}
			],
			"SkyToGround": [
				{
					"File": "anim/Sky2Ground.motion3.json"
				}
			],
			"GroundToSky": [
				{
					"File": "anim/Ground2Sky.motion3.json"
				}
			],
			"Surprised": [
				{
					"File": "anim/헤까닥.motion3.json"
				}
			],
			"Annoyed": [
				{
					"File": "anim/화남.motion3.json"
				}
			],
			"SkyClick": [
				{
					"File": "anim/SkyClicked.motion3.json"
				}
			],
			"SleepEnter": [
				{
					"File": "anim/EnterSleep.motion3.json"
				}
			],
			"SleepExit": [
				{
					"File": "anim/ExitSleep.motion3.json"
				}
			],
			"PettingLoop": [
				{
					"File": "anim/PetLoop.motion3.json"
				}
			],
			"SleepingLoop": [
				{
					"File": "anim/SleepLoop.motion3.json"
				}
			],
			"PetExit": [
				{
					"File": "anim/ExitPet.motion3.json"
				}
			],
			"PetEnter": [
				{
					"File": "anim/EnterPet.motion3.json"
				}
			]
		}
	},
	"Groups": [
		{
			"Target": "Parameter",
			"Name": "EyeBlink",
			"Ids": []
		},
		{
			"Target": "Parameter",
			"Name": "LipSync",
			"Ids": []
		}
	],
	"HitAreas": [
		{
			"Id": "HitArea",
			"Name": "Head"
		},
		{
			"Id": "HitArea2",
			"Name": "Body"
		}
	]
}